osm2gmns/__init__.py
osm2gmns/bin/bunzip.exe
osm2gmns/bin/bzcat.exe
osm2gmns/bin/bzip2.exe
osm2gmns/bin/bzip2recover.exe
osm2gmns/bin/CartConvert.exe
osm2gmns/bin/concrt140.dll
osm2gmns/bin/concrt140d.dll
osm2gmns/bin/ConicProj.exe
osm2gmns/bin/GeoConvert.exe
osm2gmns/bin/GeodesicProj.exe
osm2gmns/bin/GeodSolve.exe
osm2gmns/bin/GeoidEval.exe
osm2gmns/bin/Gravity.exe
osm2gmns/bin/IntersectTool.exe
osm2gmns/bin/MagneticField.exe
osm2gmns/bin/msvcp140.dll
osm2gmns/bin/msvcp140_1.dll
osm2gmns/bin/msvcp140_1d.dll
osm2gmns/bin/msvcp140_2.dll
osm2gmns/bin/msvcp140_2d.dll
osm2gmns/bin/msvcp140_atomic_wait.dll
osm2gmns/bin/msvcp140_codecvt_ids.dll
osm2gmns/bin/msvcp140d.dll
osm2gmns/bin/msvcp140d_atomic_wait.dll
osm2gmns/bin/msvcp140d_codecvt_ids.dll
osm2gmns/bin/Planimeter.exe
osm2gmns/bin/RhumbSolve.exe
osm2gmns/bin/TransverseMercatorProj.exe
osm2gmns/bin/vcruntime140.dll
osm2gmns/bin/vcruntime140_1.dll
osm2gmns/bin/vcruntime140_1d.dll
osm2gmns/bin/vcruntime140d.dll
osm2gmns/bin/xmlwf.exe
osm2gmns/bin/zlib.dll
osm2gmns/downloader.py
osm2gmns/include/bzlib.h
osm2gmns/include/expat.h
osm2gmns/include/expat_config.h
osm2gmns/include/expat_external.h
osm2gmns/include/GeographicLib/Accumulator.hpp
osm2gmns/include/GeographicLib/AlbersEqualArea.hpp
osm2gmns/include/GeographicLib/AuxAngle.hpp
osm2gmns/include/GeographicLib/AuxLatitude.hpp
osm2gmns/include/GeographicLib/AzimuthalEquidistant.hpp
osm2gmns/include/GeographicLib/CassiniSoldner.hpp
osm2gmns/include/GeographicLib/CircularEngine.hpp
osm2gmns/include/GeographicLib/Config.h
osm2gmns/include/GeographicLib/Constants.hpp
osm2gmns/include/GeographicLib/DAuxLatitude.hpp
osm2gmns/include/GeographicLib/DMS.hpp
osm2gmns/include/GeographicLib/DST.hpp
osm2gmns/include/GeographicLib/Ellipsoid.hpp
osm2gmns/include/GeographicLib/EllipticFunction.hpp
osm2gmns/include/GeographicLib/GARS.hpp
osm2gmns/include/GeographicLib/Geocentric.hpp
osm2gmns/include/GeographicLib/GeoCoords.hpp
osm2gmns/include/GeographicLib/Geodesic.hpp
osm2gmns-1.0.1.dist-info/METADATA
osm2gmns-1.0.1.dist-info/WHEEL
osm2gmns-1.0.1.dist-info/licenses/LICENSE
osm2gmns-1.0.1.dist-info/RECORD
