Metadata-Version: 2.2
Name: osm2gmns
Version: 1.0.1
Summary: convert map data from OpenStreetMap to network files in GMNS format
Author-Email: Jiawei Lu <lujiaweiwk@gmail.com>, "Xuesong (Simon) Zhou" <xzhou74@asu.edu>
Classifier: License :: OSI Approved :: GNU General Public License v3 or later (GPLv3+)
Classifier: Programming Language :: Python :: 3 :: Only
Classifier: Programming Language :: Python :: 3.8
Classifier: Programming Language :: Python :: 3.9
Classifier: Programming Language :: Python :: 3.10
Classifier: Programming Language :: Python :: 3.11
Classifier: Programming Language :: Python :: 3.12
Project-URL: Source Code, https://github.com/jiawlu/OSM2GMNS
Project-URL: Bug Tracker, https://github.com/jiawlu/OSM2GMNS/issues
Requires-Python: >=3.8
